dhnx/__init__.py
dhnx/components.csv
dhnx/dhn_from_osm.py
dhnx/graph.py
dhnx/helpers.py
dhnx/input_output.py
dhnx/model.py
dhnx/network.py
dhnx/plotting.py
dhnx/simulation.py
dhnx/component_attrs/consumers.csv
dhnx/component_attrs/environment.csv
dhnx/component_attrs/forks.csv
dhnx/component_attrs/pipes.csv
dhnx/component_attrs/producers.csv
dhnx/gistools/__init__.py
dhnx/gistools/connect_points.py
dhnx/gistools/geometry_operations.py
dhnx/optimization/__init__.py
dhnx/optimization/add_components.py
dhnx/optimization/dhs_nodes.py
dhnx/optimization/oemof_heatpipe.py
dhnx/optimization/optimization_models.py
dhnx/optimization/precalc_hydraulic.py
dhnx-0.0.3.dist-info/AUTHORS.rst
dhnx-0.0.3.dist-info/LICENSE
dhnx-0.0.3.dist-info/METADATA
dhnx-0.0.3.dist-info/WHEEL
dhnx-0.0.3.dist-info/top_level.txt
dhnx-0.0.3.dist-info/RECORD
