Metadata-Version: 2.1
Name: dhnx
Version: 0.0.3
Summary: Simulation and optimization of district heating and cooling networks
Author: oemof developer group
Author-email: jann.launer@rl-institut.de, johannes-roeder@uni-bremen.de
License-File: LICENSE
License-File: AUTHORS.rst
Requires-Dist: pandas (>=0.18.0)
Requires-Dist: matplotlib
Requires-Dist: networkx
Requires-Dist: pillow
Requires-Dist: folium
Requires-Dist: addict
Requires-Dist: oemof.solph (>=0.5.0)
Requires-Dist: scipy (>=1.5)
Provides-Extra: cartopy
Requires-Dist: cartopy ; extra == 'cartopy'
Provides-Extra: geopandas
Requires-Dist: geopandas ; extra == 'geopandas'
Provides-Extra: osmnx
Requires-Dist: osmnx (>=0.16.1) ; extra == 'osmnx'
Provides-Extra: tests
Requires-Dist: geopandas ; extra == 'tests'
Requires-Dist: osmnx ; extra == 'tests'
Requires-Dist: CoolProp ; extra == 'tests'
